setup.cfg
setup.py
PyShirtsIO.egg-info/PKG-INFO
PyShirtsIO.egg-info/SOURCES.txt
PyShirtsIO.egg-info/dependency_links.txt
PyShirtsIO.egg-info/requires.txt
PyShirtsIO.egg-info/top_level.txt
ShirtsIO/__init__.py
ShirtsIO/helpers.py
ShirtsIO/request.py