Metadata-Version: 1.0
Name: PyShirtsIO
Version: 0.0.1
Summary: A Python API wrapper for Shirts.io
Home-page: https://github.com/tklovett/PyShirtsIO
Author: Thomas Lovett
Author-email: tklovett@gmail.com
License: LICENSE
Platform: UNKNOWN
